{
	"Tags":
	{
		"Node":
		[
			{
				"TagName":"InputUserSettings.Profiles.Default"
			},
			{
				"TagName":"InputUserSettings.FailureReasons.InvalidMappingName"
			},
			{
				"TagName":"InputUserSettings.Profiles.Define"
			},
			{
				"TagName":"InputTag.Move"
			},
			{
				"TagName":"InputTag.LightAttack"
			},
			{
				"TagName":"InputTag.HeavyAttack"
			},
			{
				"TagName":"Player.Event.Equip.Weapon"
			},
			{
				"TagName":"Player.Event.Unequip.Weapon"
			},
			{
				"TagName":"Player.Event.Rage"
			},
			{
				"TagName":"Player.Event.Anger"
			},
			{
				"TagName":"Test.Gameplay.Attack"
			}
		]
	}
}