<version ID="1.0">
	<Window name="sceneMenu" x="0" y="0" width="1024" height="768" style="MenuBG"/>
	<Font fontname="微软雅黑" width="10" height="12" weight = "10" id = "0"/>
	<Menu name="menu" x="0" y="0" width="1920" height="26" style="menu_test">
		<item name="File" text="File" type="button" width ="100" style="menu_test"/>
			<item name="NewScen" text="New Scene" type="button" width ="100" style="menu_test"/>
			<item name="OpenScene" text="Open Scene" type="button" width ="100" style="menu_test"/>
			<item name="Save" text="Save" type="button" width ="100" style="menu_test"/>
			<item name="SaveAs" text="Save As..." type="button" width ="100" style="menu_test"/>
			<item name="NewProject" text="New Project..." type="button" width ="100" style="menu_test"/>
			<item name="OpenProject" text="Open Project..." type="button" width ="100" style="menu_test"/>
			<item name="SaveProject" text="Save Project..." type="button" width ="100" style="menu_test"/>	
			<item name="BuildSetting" text="Build Setting" type="button" width ="100" style="menu_test"/>
			<item name="BuildAndRun" text="Build And Run" type="button" width ="100" style="menu_test"/>
			<item name="Exit" text="Exit" type="button" width ="100" style="menu_test"/>	
		<item name="Edit" text="Edit" type="button" width="100" style="menu_test"/>		
		<item name="Assets" text="Assets" type="button" width="100" style="menu_test"/>	
		<item name="GameObject" text="GameObject" type="button" width="100" style="menu_test"/>		
		<item name="Component" text="Component" type="button" width="100" style="menu_test"/>		
		<item name="Cinemachine" text="Cinemachine" type="button" width="100" style="menu_test"/>		
		<item name="Window" text="Window" type="button" width="100" style="menu_test"/>		
		<item name="Help" text="Help" type="button" width="100" style="menu_test"/>			
	</Menu>
</version>